chd_rs_py-0.1.5.dist-info/METADATA
chd_rs_py-0.1.5.dist-info/WHEEL
chd/__init__.py
chd/chd.cpython-37m-x86_64-linux-gnu.so
chd_rs_py-0.1.5.dist-info/RECORD
