Metadata-Version: 2.1
Name: chd-rs-py
Version: 0.1.5
Classifier: Programming Language :: Rust
Classifier: Operating System :: POSIX :: Linux
Classifier: Operating System :: Microsoft :: Windows
Summary: Python bindings to chd-rs
Requires-Python: >=3.7
